sunrisesunset/__init__.py
sunrisesunset/sunrisesunset.py
sunrisesunset-1.0.0.dist-info/LICENSE.md
sunrisesunset-1.0.0.dist-info/METADATA
sunrisesunset-1.0.0.dist-info/WHEEL
sunrisesunset-1.0.0.dist-info/top_level.txt
sunrisesunset-1.0.0.dist-info/RECORD
