Metadata-Version: 2.1
Name: sunrisesunset
Version: 1.0.0
Summary: This class provides the sunrise and sunset times for various zeniths, latitudes and longitudes.
Home-page: https://github.com/cnobile2012/sunrisesunset
Author: Carl J. Nobile
Author-email: carl.nobile@gmail.com
License: MIT
Classifier: Development Status :: 5 - Production/Stable
Classifier: Intended Audience :: Developers
Classifier: License :: OSI Approved :: MIT License
Classifier: Operating System :: OS Independent
Classifier: Programming Language :: Python :: 3
Classifier: Programming Language :: Python :: 3.8
Classifier: Programming Language :: Python :: 3.9
Classifier: Programming Language :: Python :: 3.10
Classifier: Programming Language :: Python :: 3.11
Classifier: Topic :: Scientific/Engineering :: Astronomy
License-File: LICENSE.md
